nlpe/__init__.py
nlpe/argument.py
nlpe/pool.py
nlpe/proxy.py
nlpe/approach/__init__.py
nlpe/approach/approach.py
nlpe/data/__init__.py
nlpe/data/data.py
nlpe/data/text.py
nlpe/evaluator/__init__.py
nlpe/evaluator/evaluator.py
nlpe/utils/__init__.py
nlpe/utils/design_patterns.py
nlpe/utils/glossary.py
nlpe/utils/log.py
nlpe/utils/test.py
nlpe/utils/utils.py
nlpe-0.0.6.dist-info/METADATA
nlpe-0.0.6.dist-info/WHEEL
nlpe-0.0.6.dist-info/licenses/LICENSE
nlpe-0.0.6.dist-info/RECORD
