Metadata-Version: 2.3
Name: nlpe
Version: 0.0.6
Summary: A Python library for NLP experiments.
Author-email: 徐 勝 <gocodedoc@gmail.com>
License: MIT License
License-File: LICENSE
Classifier: License :: OSI Approved :: MIT License
Classifier: Operating System :: OS Independent
Classifier: Programming Language :: Python :: 3
Requires-Python: >=3.11
Requires-Dist: pytest
